{"inputFile":"","dataFlowName": "DC_E_ERBSG2","setType":"Adapter","setName":"Adapter_INTF_DC_E_ERBS_mdc","actionContents":{"outDir":"H:\\git\\testing\\mdc\\output","maxFilesPerRun":"10000","dublicateCheck":"true","thresholdMethod":"more","inDir":"H:\\git\\testing\\mdc\\","interfaceName":"INTF_DC_E_ERBS","ProcessedFiles.fileNameFormat":"","minFileAge":"1","baseDir":"H:\\git\\testing\\mdc","archivePeriod":"168","useZip":"gzip","loaderDir":"/root/mdc/sbkafka/","parserType":"mdc","doubleCheckAction":"delete","ProcessedFiles.processedDir":"H:\\git\\testing\\mdc","failedAction":"move","dirThreshold":"0","workers":"3","afterParseAction":"delete","MDCParser.HashData":"true","MDCParser.UseVector":"TRUE","MDCParser.readVendorIDFrom":"data","MDCParser.vendorIDMask":".*,(.*)\\=.*","MDCParser.createOwnVectorFile":"TRUE","MDCParser.hasFlexCounters":"TRUE","MDCParser.createOwnFlexFile":"TRUE","outputFormat":"0"}}